census_backup/__init__.py
census_backup/main.py
census_backup-0.1.10.dist-info/METADATA
census_backup-0.1.10.dist-info/WHEEL
census_backup-0.1.10.dist-info/entry_points.txt
census_backup-0.1.10.dist-info/RECORD
