Metadata-Version: 2.1
Name: census_backup
Version: 0.1.10
Summary: Backup utilities.
Author: Your Name
Author-email: you@example.com
Requires-Python: >=3.11,<4.0
Classifier: Programming Language :: Python :: 3
Classifier: Programming Language :: Python :: 3.11
Classifier: Programming Language :: Python :: 3.12
Requires-Dist: censusdis (>=1.3.3,<2.0.0)
Requires-Dist: logargparser (>=0.1.1,<0.2.0)
Requires-Dist: usingversion (>=0.1.2,<0.2.0)
